README.md
setup.py
MCS030897/__init__.py
MCS030897/a.py
MCS030897.egg-info/PKG-INFO
MCS030897.egg-info/SOURCES.txt
MCS030897.egg-info/dependency_links.txt
MCS030897.egg-info/requires.txt
MCS030897.egg-info/top_level.txt